{
  "table_id": "table_122",
  "page": 157,
  "rows": 3,
  "columns": 7,
  "bbox": [
    22.230000495910645,
    700.1699829101562,
    546.9700012207031,
    760.1600036621094
  ],
  "source_method": "pymupdf_find_tables",
  "csv_path": "tables/table_122.csv",
  "json_path": "tables/table_122.json",
  "title_candidate": "单位：元",
  "section_candidate": "5 年以上",
  "blank_cell_ratio": 0.2857,
  "numeric_cell_ratio": 0.3333,
  "data": [
    [
      "项目",
      "期末余额",
      "",
      "",
      "期初余额",
      "",
      ""
    ],
    [
      "",
      "账面余额",
      "存货跌价准备/\n合同履约成本\n减值准备",
      "账面价值",
      "账面余额",
      "存货跌价准备/\n合同履约成本\n减值准备",
      "账面价值"
    ],
    [
      "原材料",
      "107,710,787.80",
      "679,929.85",
      "107,030,857.95",
      "118,214,019.54",
      "",
      "118,214,019.54"
    ]
  ]
}
