{
  "table_id": "table_224",
  "page": 200,
  "rows": 10,
  "columns": 5,
  "bbox": [
    89.97999954223633,
    534.3699951171875,
    542.6199951171875,
    757.4100036621094
  ],
  "source_method": "pymupdf_find_tables",
  "csv_path": "tables/table_224.csv",
  "json_path": "tables/table_224.json",
  "title_candidate": "单位：元",
  "section_candidate": "十三、",
  "blank_cell_ratio": 0.72,
  "numeric_cell_ratio": 0.0,
  "data": [
    [
      "项目",
      "期末公允价值",
      "",
      "",
      ""
    ],
    [
      "",
      "第一层次公允价\n值计量",
      "第二层次公允\n价值计量",
      "第三层次公允价\n值计量",
      "合计"
    ],
    [
      "一、持续的公允价值计\n量",
      "",
      "",
      "",
      ""
    ],
    [
      "（一）交易性金融资产",
      "",
      "",
      "",
      ""
    ],
    [
      "1.以公允价值计量且变\n动计入当期损益的金融\n资产",
      "",
      "",
      "",
      ""
    ],
    [
      "（1）债务工具投资",
      "",
      "",
      "",
      ""
    ],
    [
      "（2）权益工具投资",
      "",
      "",
      "",
      ""
    ],
    [
      "（3）衍生金融资产",
      "",
      "",
      "",
      ""
    ],
    [
      "2. 指定以公允价值计量\n且其变动计入当期损益\n的金融资产",
      "",
      "",
      "",
      ""
    ],
    [
      "（1）债务工具投资",
      "",
      "",
      "",
      ""
    ]
  ]
}
